missmixed/__init__.py
missmixed/miss_mixed.py
missmixed/run.py
missmixed/architecture/__init__.py
missmixed/architecture/architecture.py
missmixed/architecture/deep_imputer.py
missmixed/utils/__init__.py
missmixed/utils/shared_data.py
missmixed/utils/utils.py
missmixed-1.1.0.dist-info/LICENSE.txt
missmixed-1.1.0.dist-info/METADATA
missmixed-1.1.0.dist-info/WHEEL
missmixed-1.1.0.dist-info/entry_points.txt
missmixed-1.1.0.dist-info/top_level.txt
missmixed-1.1.0.dist-info/RECORD
