Metadata-Version: 2.1
Name: missmixed
Version: 1.1.0
Summary: An Adaptive, Extensible and Configurable Multi-Layer Framework for Iterative Missing Value Imputation
Home-page: https://github.com/MohammadKlhr/missmixed
Author: Mohammad Mahdi Kalhori
Author-email: Mohammad Mahdi Kalhori <mohammad.mahdi.kalhor.99@gmail.com>, Fateme Akbari <fatemeeakbari.97@gmail.com>
Maintainer: Mohammad Mahdi Kalhori, Fateme Akbari
Maintainer-email: mohammad.mahdi.kalhor.99@gmail.com, fatemeeakbari.97@gmail.com
License: MIT License
Keywords: missing data,missing data imputation,machine learning,data science,preprocessing
Requires-Python: >=3.10
License-File: LICENSE.txt
Requires-Dist: tqdm>=4.66
Requires-Dist: pandas>=2.0.0
Requires-Dist: numpy>=1.23
Requires-Dist: scikit-learn>=1.4
Requires-Dist: scipy>=1.6.0
Provides-Extra: deep
Requires-Dist: tensorflow>=2.12; extra == "deep"
Provides-Extra: ml
Requires-Dist: xgboost>=3.0; extra == "ml"
